{
  "songs": [
    {
      "starred": false,
      "popularity": 80.0,
      "starredNum": 0,
      "playedNum": 0,
      "dayPlays": 0,
      "hearTime": 0,
      "mp3Url": "http://m2.music.126.net/f-bG9XwJiy_eJ9XYk2EVSw==/6033020301634728.mp3",
      "rtUrls": [],
      "name": "Morning",
      "id": 28240577,
      "position": 2,
      "duration": 321933,
      "status": 0,
      "alias": [],
      "artists": [
        {
          "img1v1Id": 0,
          "name": "Beck",
          "id": 29320,
          "alias": [],
          "briefDesc": "",
          "picUrl": "http://p3.music.126.net/6y-UleORITEDbvrOLV0Q8A==/5639395138885805.jpg",
          "picId": 0,
          "albumSize": 0,
          "img1v1Url": "http://p4.music.126.net/6y-UleORITEDbvrOLV0Q8A==/5639395138885805.jpg",
          "musicSize": 0,
          "trans": ""
        }
      ],
      "score": 80,
      "album": {
        "songs": [],
        "name": "Morning Phase",
        "id": 2757010,
        "type": "专辑",
        "size": 13,
        "status": 0,
        "description": "",
        "tags": "",
        "alias": [],
        "artists": [
          {
            "img1v1Id": 0,
            "name": "Beck",
            "id": 29320,
            "alias": [],
            "briefDesc": "",
            "picUrl": "http://p4.music.126.net/6y-UleORITEDbvrOLV0Q8A==/5639395138885805.jpg",
            "picId": 0,
            "albumSize": 0,
            "img1v1Url": "http://p4.music.126.net/6y-UleORITEDbvrOLV0Q8A==/5639395138885805.jpg",
            "musicSize": 0,
            "trans": ""
          }
        ],
        "briefDesc": "",
        "artist": {
          "img1v1Id": 0,
          "name": "",
          "id": 0,
          "alias": [],
          "briefDesc": "",
          "picUrl": "http://p4.music.126.net/6y-UleORITEDbvrOLV0Q8A==/5639395138885805.jpg",
          "picId": 0,
          "albumSize": 0,
          "img1v1Url": "http://p4.music.126.net/6y-UleORITEDbvrOLV0Q8A==/5639395138885805.jpg",
          "musicSize": 0,
          "trans": ""
        },
        "picUrl": "http://p3.music.126.net/CxhwMxVCfvBHr48WX866hg==/2537672837919114.jpg",
        "picId": 2537672837919114,
        "commentThreadId": "R_AL_3_2757010",
        "publishTime": 1393257600007,
        "company": "Capitol Records",
        "copyrightId": 0,
        "pic": 2537672837919114,
        "blurPicUrl": "http://p3.music.126.net/CxhwMxVCfvBHr48WX866hg==/2537672837919114.jpg",
        "companyId": 0
      },
      "fee": 0,
      "mMusic": {
        "name": "Morning",
        "id": 46270074,
        "size": 6476626,
        "extension": "mp3",
        "dfsId": 6050612487687443,
        "playTime": 321933,
        "bitrate": 160000,
        "sr": 44100,
        "volumeDelta": -0.53
      },
      "lMusic": {
        "name": "Morning",
        "id": 46270075,
        "size": 3900743,
        "extension": "mp3",
        "dfsId": 6033020301634728,
        "playTime": 321933,
        "bitrate": 96000,
        "sr": 44100,
        "volumeDelta": -0.55
      },
      "commentThreadId": "R_SO_4_28240577",
      "hMusic": {
        "name": "Morning",
        "id": 46270073,
        "size": 12916331,
        "extension": "mp3",
        "dfsId": 6045114929555554,
        "playTime": 321933,
        "bitrate": 320000,
        "sr": 44100,
        "volumeDelta": -0.95
      },
      "copyrightId": 0,
      "mvid": 0,
      "ftype": 0,
      "rtype": 0,
      "rurl": null,
      "copyFrom": "",
      "bMusic": {
        "name": "Morning",
        "id": 46270075,
        "size": 3900743,
        "extension": "mp3",
        "dfsId": 6033020301634728,
        "playTime": 321933,
        "bitrate": 96000,
        "sr": 44100,
        "volumeDelta": -0.55
      },
      "audition": {
        "name": "Morning",
        "id": 46227688,
        "size": 2607154,
        "extension": "m4a",
        "dfsId": 5985741301622978,
        "playTime": 321933,
        "bitrate": 64000,
        "sr": 44100,
        "volumeDelta": 0.0
      },
      "ringtone": "",
      "disc": "",
      "no": 2,
      "crbt": "96ae3c0f585614038377dab84dcfc1fc",
      "rtUrl": null
    }
  ],
  "equalizers": {},
  "code": 200
}
